Workbook

Sheet Alcance y tiempos
A1: AgroQuality — Alcance del Proyecto y Tiempos
A2: Qué se entrega y en cuánto tiempo. App móvil para el inspector + plataforma web para la gerencia.
A4: Componente | B4: Entregable | C4: Estado | D4: Tiempo (días)
A5: App del inspector (móvil) | B5: Puesta en marcha de la app móvil y personalización con la marca AgroQuality | C5: Desarrollo nuevo | D5: 0.5
A6: App del inspector (móvil) | B6: Funcionamiento sin conexión: las inspecciones se registran en campo aunque no haya señal y se sincronizan solas al volver el internet | C6: Desarrollo nuevo | D6: 1
A7: App del inspector (móvil) | B7: Formulario de inspección completo: datos del lote, pallets, defectos, termografía y fotos | C7: Desarrollo nuevo | D7: 3
A8: App del inspector (móvil) | B8: Listado de inspecciones del inspector y experiencia de uso final | C8: Desarrollo nuevo | D8: 1
A9: Plataforma de gerencia (web) | B9: Panel de gerencia: indicadores de calidad, resultados por lote y principales defectos | C9: Ya disponible | D9: 0
A10: Plataforma de gerencia (web) | B10: Revisión de los reportes de inspección | C10: Ya disponible | D10: 0
A11: Plataforma de gerencia (web) | B11: Puesta a punto para el uso real con los datos del equipo de campo | C11: Desarrollo nuevo | D11: 1
A12: Sistema y seguridad | B12: Sistema central y separación de la información por empresa (los datos de Marand solo los ve Marand) | C12: Ya disponible | D12: 0
A13: Sistema y seguridad | B13: Publicación segura en la nube | C13: Desarrollo nuevo | D13: 0.5
A14: Puesta en marcha | B14: Pruebas completas de todo el flujo: captura en campo hasta la llegada al panel de gerencia | C14: Desarrollo nuevo | D14: 1.5
A15: Puesta en marcha | B15: Capacitación al equipo y acompañamiento en el arranque | C15: Desarrollo nuevo | D15: 0.5
A16: Tiempo total estimado | D16: =SUM(D5:D15) -> 9
A18: Equivale a aproximadamente | B18: de desarrollo (a 5 días por semana) | D18: =D16/5 -> 1.8
A20: Resumen por componente
A21: Componente | B21: Tiempo (días)
A22: App del inspector (móvil) | B22: =SUMIF($A$5:$A$15,A22,$D$5:$D$15) -> 5.5
A23: Plataforma de gerencia (web) | B23: =SUMIF($A$5:$A$15,A23,$D$5:$D$15) -> 1
A24: Sistema y seguridad | B24: =SUMIF($A$5:$A$15,A24,$D$5:$D$15) -> 0.5
A25: Puesta en marcha | B25: =SUMIF($A$5:$A$15,A25,$D$5:$D$15) -> 2
A26: Total | B26: =SUM(B22:B25) -> 9
A28: Buena parte de la plataforma —el panel de gerencia, el sistema central y la seguridad— ya está construida y se incluye sin costo adicional. El tiempo y la inversión se concentran en la app móvil del inspector, hecha a medida para Marand.

Sheet Inversión
A1: AgroQuality — Inversión
A2: Pago único de desarrollo + suscripción mensual. Montos en soles (PEN).
A4: Condiciones (editables)
A5: Pago único — desarrollo e implementación | B5: 3500
A6: Plan piloto — tarifa / mes (meses 1-2) | B6: 600
A7: Plan AgroQuality — tarifa / mes (desde mes 3) | B7: 1200
A8: Meses de piloto | B8: 2
A9: Meses facturados — primer año | B9: 12
A10: IGV | B10: 0.18
A13: Detalle de inversión — primer año
A14: Concepto | B14: Cantidad | C14: Precio unit. (S/) | D14: Subtotal (S/)
A15: Desarrollo e implementación (pago único) | B15: 1 | C15: =$B$5 -> 3500 | D15: =B15*C15 -> 3500
A16: Plan piloto (meses 1-2) | B16: =$B$8 -> 2 | C16: =$B$6 -> 600 | D16: =B16*C16 -> 1200
A17: Plan AgroQuality (resto del primer año) | B17: =$B$9-$B$8 -> 10 | C17: =$B$7 -> 1200 | D17: =B17*C17 -> 12000
A18: Subtotal (sin IGV) | D18: =SUM(D15:D17) -> 16700
A19: IGV (18%) | D19: =D18*$B$10 -> 3006
A20: TOTAL primer año (con IGV) | D20: =D18+D19 -> 19706
A22: Costo de los siguientes años (suscripción anual, sin IGV) | D22: =$B$9*$B$7 -> 14400
A23: El desarrollo se paga una sola vez al inicio. La suscripción incluye alojamiento, operación, mantenimiento, respaldos y las mejoras futuras, sin costo adicional.

Sheet Opción suscripción
A1: AgroQuality — Opción suscripción (sin pago inicial)
A2: El desarrollo se incluye dentro de la mensualidad: Marand no realiza ningún desembolso al inicio.
A4: Condiciones (editables)
A5: Desarrollo incluido en la mensualidad (S/) | B5: =Inversión!$B$5 -> 3500
A6: Meses de permanencia | B6: 12
A7: Mensualidad base (operación, S/) | B7: =Inversión!$B$7 -> 1200
A8: Meses facturados — primer año | B8: =Inversión!$B$9 -> 12
A9: IGV | B9: =Inversión!$B$10 -> 0.18
A11: Cómo se compone la mensualidad
A12: Parte mensual del desarrollo | B12: =B5/B6 -> 291.66667
A13: Mensualidad total (operación + desarrollo) | B13: =B7+B12 -> 1491.6667
A14: Mensualidad desde el año 2 (ya recuperado) | B14: =B7 -> 1200
A16: Resultado — primer año
A17: Suscripción año 1 (meses × mensualidad total) | B17: =B8*B13 -> 17900
A18: IGV (18%) | B18: =B17*B9 -> 3222
A19: TOTAL primer año (con IGV) | B19: =B17+B18 -> 21122
A21: Comparación de las dos opciones
A22: Concepto | B22: Con pago inicial | C22: Sin pago inicial
A23: Pago al inicio | B23: =Inversión!$B$5 -> 3500 | C23: 0
A24: Mensualidad (régimen) | B24: =Inversión!$B$7 -> 1200 | C24: =B13 -> 1491.6667
A25: Total primer año (sin IGV) | B25: =Inversión!$D$18 -> 16700 | C25: =B17 -> 17900
A26: Total primer año (con IGV) | B26: =Inversión!$D$20 -> 19706 | C26: =B19 -> 21122
A27: Costo anual desde el año 2 | B27: =Inversión!$D$22 -> 14400 | C27: =B8*B14 -> 14400
A29: Con esta opción Marand no paga nada al inicio: el desarrollo se reparte dentro de la mensualidad durante el período de permanencia. Cumplido ese período, la mensualidad baja a la tarifa de operación.
